agnews/__init__.py
agnews/scraper.py
agnews-0.0.1.dist-info/METADATA
agnews-0.0.1.dist-info/WHEEL
agnews-0.0.1.dist-info/licenses/LICENSE
agnews-0.0.1.dist-info/RECORD
